{
  "project_info": {
    "project_number": "322395320128",
    "project_id": "metaxpertserp",
    "storage_bucket": "metaxpertserp.appspot.com"
  },
  "client": [
    {
      "client_info": {
        "mobilesdk_app_id": "1:322395320128:android:ed3539b89dbbc2da7114a5",
        "android_client_info": {
          "package_name": "com.aafdev1.my_loc"
        }
      },
      "oauth_client": [],
      "api_key": [
        {
          "current_key": "AIzaSyDG11b1WW3tjXDKfdHiXF2_QX4XezB2xiY"
        }
      ],
      "services": {
        "appinvite_service": {
          "other_platform_oauth_client": []
        }
      }
    }
  ],
  "configuration_version": "1"
}